LICENSE
MANIFEST.in
README.md
pyproject.toml
setup.cfg
setup.py
data/io.github.rdybka.vht.desktop
data/io.github.rdybka.vht.metainfo.xml
data/io.github.rdybka.vht.png
data/mandy.png
data/menu.ui
data/menu_norend.ui
data/vht.svg
data/bank/10-gm1
data/bank/20-gm2
data/ctrl/10-gm
data/ctrl/20-zyn
doc/io.github.rdybka.vht.yml
doc/vht.1.gz
doc/vht.1.md
libvht/__init__.py
libvht/ctrlrow.c
libvht/ctrlrow.h
libvht/envelope.c
libvht/envelope.h
libvht/jack_process.c
libvht/jack_process.h
libvht/libcvht.h
libvht/libcvht.py
libvht/libcvht_wrap.c
libvht/libvht.c
libvht/mandy.c
libvht/mandy.h
libvht/mandy_pix_scan.c
libvht/mandy_pix_scan.h
libvht/mandy_trk_disp.c
libvht/mandy_trk_disp.h
libvht/midi_client.c
libvht/midi_client.h
libvht/midi_event.c
libvht/midi_event.h
libvht/module.c
libvht/module.h
libvht/row.c
libvht/row.h
libvht/sequence.c
libvht/sequence.h
libvht/smf.c
libvht/smf.h
libvht/stolen.c
libvht/timeline.c
libvht/timeline.h
libvht/track.c
libvht/track.h
libvht/tracy.c
libvht/tracy.h
libvht/vhtcolumn.py
libvht/vhtctrl.py
libvht/vhtctrllist.py
libvht/vhtctrlrow.py
libvht/vhtextras.py
libvht/vhtmandy.py
libvht/vhtmodule.py
libvht/vhtport.py
libvht/vhtports.py
libvht/vhtquicklist.py
libvht/vhtrow.py
libvht/vhtsequence.py
libvht/vhttimeline.py
libvht/vhttimelinechange.py
libvht/vhttimelinechanges.py
libvht/vhttimelineloop.py
libvht/vhttimelineslices.py
libvht/vhttimelinestrip.py
libvht/vhttimelinestrips.py
libvht/vhttimelineticks.py
libvht/vhttrack.py
libvht/vhttracy.py
vht/__init__.py
vht/autoexec.py
vht/bankcfg.py
vht/capturebutton.py
vht/codedaemon.py
vht/configuration.py
vht/console.py
vht/controllereditor.py
vht/controllersview.py
vht/controllersviewrow.py
vht/controllerundobuffer.py
vht/ctrlcfg.py
vht/extras.py
vht/filerotator.py
vht/main.py
vht/mainwin.py
vht/mandymenu.py
vht/mandyview.py
vht/midimapview.py
vht/midimapviewrow.py
vht/notebooklabel.py
vht/poormanspiano.py
vht/portconfig.py
vht/portconfigpopover.py
vht/portconfigview.py
vht/preferenceswin.py
vht.egg-info/PKG-INFO
vht.egg-info/SOURCES.txt
vht.egg-info/dependency_links.txt
vht.egg-info/entry_points.txt
vht.egg-info/top_level.txt