Metadata-Version: 2.1
Name: vht
Version: 0.4.6
Summary: vahatraker - a live MIDI sequencer for pipewire/JACK
Home-page: https://github.com/rdybka/vht
Author: Remigiusz Dybka
Author-email: remigiusz.dybka@gmail.com
License: GPLv3+
Classifier: Development Status :: 5 - Production/Stable
Classifier: Environment :: X11 Applications :: GTK
Classifier: Intended Audience :: End Users/Desktop
Classifier: License :: OSI Approved :: GNU General Public License v3 or later (GPLv3+)
Classifier: Programming Language :: Python :: 3
Classifier: Programming Language :: C
Classifier: Operating System :: POSIX :: Linux
Classifier: Topic :: Multimedia :: Sound/Audio :: MIDI
License-File: LICENSE
